tpi_connector/__init__.py
tpi_connector/connector.py
tpi_connector-0.1.6.dist-info/LICENSE
tpi_connector-0.1.6.dist-info/METADATA
tpi_connector-0.1.6.dist-info/WHEEL
tpi_connector-0.1.6.dist-info/top_level.txt
tpi_connector-0.1.6.dist-info/RECORD
