Metadata-Version: 2.1
Name: tpi-connector
Version: 0.1.6
Summary: Restful connector to tpi-compliance applications
Home-page: https://github.com/top-infra/tpi-connector
Author: Soral
Author-email: admin@top-infra.com
License: UNKNOWN
Platform: UNKNOWN
Classifier: Programming Language :: Python :: 3
Classifier: License :: OSI Approved :: GNU Affero General Public License v3 or later (AGPLv3+)
Classifier: Operating System :: OS Independent
Requires-Python: >=3.7
License-File: LICENSE
Requires-Dist: requests
